browser_ui/BrowserUI.py
browser_ui/__init__.py
browser_ui/injected_script.js
browser_ui/types/EventType.py
browser_ui/types/Serializable.py
browser_ui/types/__init__.py
browser_ui/utils/__init__.py
browser_ui/utils/get_caller_file_abs_path.py
browser_ui/utils/inject_script.py
browser_ui-0.3.4.dist-info/METADATA
browser_ui-0.3.4.dist-info/WHEEL
browser_ui-0.3.4.dist-info/top_level.txt
browser_ui-0.3.4.dist-info/RECORD
